aws_org_client/__init__.py
aws_org_client/cli.py
aws_org_client/client.py
aws_org_client/modules/__init__.py
aws_org_client/modules/identity_store.py
aws_org_client/modules/logger.py
aws_org_client/modules/organizations.py
aws_org_client/modules/paginator.py
aws_org_client/modules/sso_admin.py
aws_org_client-0.0.17.dist-info/METADATA
aws_org_client-0.0.17.dist-info/WHEEL
aws_org_client-0.0.17.dist-info/entry_points.txt
aws_org_client-0.0.17.dist-info/RECORD
