Metadata-Version: 2.1
Name: aws-org-client
Version: 0.0.17
Summary: Browse and manage AWS identity and organization resources.
Home-page: https://github.com/hackersandslackers/python-poetry-tutorial/
Keywords: AWS,Identity Store,Organizations,SSO
Author: Sam Holden
Author-email: sam.holden@digital.cabinet-office.gov.uk
Requires-Python: >=3.11,<4.0
Classifier: Programming Language :: Python :: 3
Classifier: Programming Language :: Python :: 3.11
Classifier: Programming Language :: Python :: 3.12
Classifier: Programming Language :: Python :: 3.13
Requires-Dist: asyncio (>=3.4.3,<4.0.0)
Requires-Dist: boto3 (>=1.28.66,<2.0.0)
Requires-Dist: click (>=8.1.7,<9.0.0)
Requires-Dist: logzero (>=1.7.0,<2.0.0)
Requires-Dist: typing-extensions (>=4.8.0,<5.0.0)
Project-URL: Documentation, https://hackersandslackers.com/python-poetry/
Project-URL: Repository, https://github.com/hackersandslackers/python-poetry-tutorial/
